{"toptags": {"tag": [{"count": "100", "url": "http://www.last.fm/tag/heavy%20metal", "name": "HEAVYMETAL"}, {"count": "58", "url": "http://www.last.fm/tag/hard%20rock", "name": "HARDROCK"}, {"count": "46", "url": "http://www.last.fm/tag/classic%20rock", "name": "CLASSICROCK"}, {"count": "43", "url": "http://www.last.fm/tag/metal", "name": "METAL"}, {"count": "29", "url": "http://www.last.fm/tag/rock", "name": "ROCK"}, {"count": "20", "url": "http://www.last.fm/tag/doom%20metal", "name": "DOOMMETAL"}, {"count": "9", "url": "http://www.last.fm/tag/british", "name": "BRITISH"}], "@attr": {"artist": "Black Sabbath"}}}